odm/__init__.py
odm/mapper.py
odm/strategy.py
odm/utils.py
odm/version.py
odm/dialects/__init__.py
odm/dialects/postgresql/__init__.py
odm/dialects/postgresql/green.py
odm/dialects/postgresql/pool.py
odm/types/__init__.py
odm/types/choice.py
odm/types/ip_address.py
odm/types/json.py
odm/types/uuid.py
pulsar_odm-0.6.2.dist-info/DESCRIPTION.rst
pulsar_odm-0.6.2.dist-info/LICENSE.txt
pulsar_odm-0.6.2.dist-info/METADATA
pulsar_odm-0.6.2.dist-info/RECORD
pulsar_odm-0.6.2.dist-info/WHEEL
pulsar_odm-0.6.2.dist-info/metadata.json
pulsar_odm-0.6.2.dist-info/top_level.txt
