Metadata-Version: 2.0
Name: pulsar-odm
Version: 0.6.2
Summary: Object Data Mapper for pulsar asynchronous framework
Home-page: https://github.com/quantmind/pulsar-odm
Author: Luca Sbardella
Author-email: luca@quantmind.com
License: BSD
Platform: UNKNOWN
Classifier: Development Status :: 4 - Beta
Classifier: Environment :: Web Environment
Classifier: Intended Audience :: Developers
Classifier: License :: OSI Approved :: BSD License
Classifier: Operating System :: OS Independent
Classifier: Programming Language :: Python
Classifier: Programming Language :: Python :: 3
Classifier: Programming Language :: Python :: 3.5
Classifier: Programming Language :: Python :: 3.6
Classifier: Topic :: Utilities
Requires-Dist: greenlet
Requires-Dist: sqlalchemy
Requires-Dist: psycopg2
Requires-Dist: pulsar
